pawfetch/__init__.py
pawfetch/__main__.py
pawfetch/__version__.py
pawfetch/color_scale.py
pawfetch/color_util.py
pawfetch/constants.py
pawfetch/font_logo.py
pawfetch/main.py
pawfetch/models.py
pawfetch/neofetch_util.py
pawfetch/presets.py
pawfetch/pride_month.py
pawfetch/py.py
pawfetch/rs.py
pawfetch/serializer.py
pawfetch/termenv.py
pawfetch/types.py
pawfetch/data/font_logos.json
pawfetch/data/presets.json
pawfetch/distros/__init__.py
pawfetch/distros/adelie.py
pawfetch/distros/aeros.py
pawfetch/distros/afterglow.py
pawfetch/distros/aix.py
pawfetch/distros/almalinux.py
pawfetch/distros/alpine.py
pawfetch/distros/alpine_small.py
pawfetch/distros/alter.py
pawfetch/distros/amazon.py
pawfetch/distros/amogos.py
pawfetch/distros/anarchy.py
pawfetch/distros/android.py
pawfetch/distros/android_small.py
pawfetch/distros/antergos.py
pawfetch/distros/antix.py
pawfetch/distros/aosc_os.py
pawfetch/distros/aperio_gnu_linux.py
pawfetch/distros/aperture.py
pawfetch/distros/apricity.py
pawfetch/distros/arch.py
pawfetch/distros/arch_old.py
pawfetch/distros/arch_small.py
pawfetch/distros/archbox.py
pawfetch/distros/archcraft.py
pawfetch/distros/archcraft_ascii.py
pawfetch/distros/archcraft_minimal.py
pawfetch/distros/archlabs.py
pawfetch/distros/archmerge.py
pawfetch/distros/archstrike.py
pawfetch/distros/arcolinux.py
pawfetch/distros/arcolinux_small.py
pawfetch/distros/arkane.py
pawfetch/distros/arselinux.py
pawfetch/distros/artix.py
pawfetch/distros/artix_small.py
pawfetch/distros/arya.py
pawfetch/distros/asahi.py
pawfetch/distros/asteroidos.py
pawfetch/distros/astos.py
pawfetch/distros/astra_linux.py
pawfetch/distros/athena.py
pawfetch/distros/azos.py
pawfetch/distros/bazzite.py
pawfetch/distros/bedrock.py
pawfetch/distros/biglinux.py
pawfetch/distros/biglinux_large.py
pawfetch/distros/bitrig.py
pawfetch/distros/blackarch.py
pawfetch/distros/blackmesa.py
pawfetch/distros/blackpanther.py
pawfetch/distros/blag.py
pawfetch/distros/blankon.py
pawfetch/distros/bluelight.py
pawfetch-2.0.4.dist-info/METADATA
pawfetch-2.0.4.dist-info/WHEEL
pawfetch-2.0.4.dist-info/entry_points.txt
pawfetch-2.0.4.dist-info/licenses/LICENSE.md
pawfetch-2.0.4.dist-info/RECORD
